alidaapis/__init__.py
alidaapis/auth.py
alidaapis/bda.py
alidaapis/dataset.py
alidaapis/datasource.py
alidaapis/minio_utils.py
alidaapis/service.py
alidaapis/utils.py
alida_apis-0.0.17.dist-info/METADATA
alida_apis-0.0.17.dist-info/WHEEL
alida_apis-0.0.17.dist-info/top_level.txt
alida_apis-0.0.17.dist-info/RECORD
