Metadata-Version: 2.1
Name: alida-apis
Version: 0.0.17
Summary: Python APIs for interaction with ALIDA backend.
Home-page: UNKNOWN
Author: Alida research team
Author-email: salvatore.cipolla@eng.it
License: UNKNOWN
Platform: UNKNOWN
Classifier: Programming Language :: Python :: 3
Classifier: License :: OSI Approved :: MIT License
Classifier: Operating System :: OS Independent
Requires-Python: >=3.6
Requires-Dist: requests
Requires-Dist: boto3
Requires-Dist: minio
Requires-Dist: progressbar
Requires-Dist: pandas
